heputl/__init__.py
heputl/logging.py
heputl/dats/statistics.py
heputl/dats/toydata.py
heputl/plotting/oneD.py
heputl/plotting/twoD.py
heputl/utils/preprocessing.py
heputl/utils/string_constants.py
heputl-0.1.0.dist-info/LICENSE
heputl-0.1.0.dist-info/METADATA
heputl-0.1.0.dist-info/WHEEL
heputl-0.1.0.dist-info/top_level.txt
heputl-0.1.0.dist-info/RECORD
