Metadata-Version: 2.1
Name: heputl
Version: 0.1.0
Summary: Utilities for high energy physics
Author-email: Kinga Anna Wozniak <kingusiu@gmail.com>
License: GPL-3.0-or-later
Classifier: Programming Language :: Python :: 3
Classifier: Operating System :: OS Independent
Requires-Python: >=3.7
